{
    "Ar36": {
        "error": 0.0001969336396413719,
        "error_type": "SEM",
        "filter_outliers_dict": {
            "filter_outliers": true,
            "iterations": 1,
            "std_devs": 3,
            "use_iqr_filtering": false,
            "use_standard_deviation_filtering": false
        },
        "fit": "linear",
        "fn": 119,
        "include_baseline_error": true,
        "n": 120,
        "outlier_excluded": [
            8
        ],
        "reviewed": true,
        "user_excluded": [],
        "value": 0.005976550273085913
    },
    "Ar37": {
        "error": 0.010776918907412891,
        "error_type": "SEM",
        "filter_outliers_dict": {
            "filter_outliers": true,
            "iterations": 1,
            "std_devs": 3,
            "use_iqr_filtering": false,
            "use_standard_deviation_filtering": false
        },
        "fit": "linear",
        "fn": 120,
        "include_baseline_error": true,
        "n": 120,
        "outlier_excluded": [],
        "reviewed": true,
        "user_excluded": [],
        "value": -0.026709719183632574
    },
    "Ar38": {
        "error": 0.005121176534310488,
        "error_type": "SEM",
        "filter_outliers_dict": {
            "filter_outliers": true,
            "iterations": 1,
            "std_devs": 3,
            "use_iqr_filtering": false,
            "use_standard_deviation_filtering": false
        },
        "fit": "linear",
        "fn": 120,
        "include_baseline_error": true,
        "n": 120,
        "outlier_excluded": [],
        "reviewed": true,
        "user_excluded": [],
        "value": 0.1523612072992976
    },
    "Ar39": {
        "error": 0.014134593542872267,
        "error_type": "SEM",
        "filter_outliers_dict": {
            "filter_outliers": true,
            "iterations": 1,
            "std_devs": 3,
            "use_iqr_filtering": false,
            "use_standard_deviation_filtering": false
        },
        "fit": "linear",
        "fn": 120,
        "include_baseline_error": true,
        "n": 120,
        "outlier_excluded": [],
        "reviewed": true,
        "user_excluded": [],
        "value": 6.391705100621343
    },
    "Ar40": {
        "error": 0.01612845548563283,
        "error_type": "SEM",
        "filter_outliers_dict": {
            "filter_outliers": true,
            "iterations": 1,
            "std_devs": 3,
            "use_iqr_filtering": false,
            "use_standard_deviation_filtering": false
        },
        "fit": "linear",
        "fn": 120,
        "include_baseline_error": true,
        "n": 120,
        "outlier_excluded": [],
        "reviewed": true,
        "user_excluded": [],
        "value": 64.2895800686567
    },
    "Ar41": {
        "error": 0.002193757280894934,
        "error_type": "SEM",
        "filter_outliers_dict": {
            "filter_outliers": true,
            "iterations": 1,
            "std_devs": 2
        },
        "fit": "Average",
        "value": 0.009429310313988653
    }
}